[
    {
        "func": "addNewToken(_uri)@uriOriginalToken[_uri]",
        "type": "PptType.EXIT",
        "executionType": "TxType.NORMAL",
        "preconditions": [
            "ori(tokenSold$bool) == false",
            "ori(tokenCreator$address) == 0",
            "ori(tokenSalePrice$uint256) == 0",
            "ori(tokenSalePrice$uint256) == 0",
            "ori(tokenSalePrice$uint256) one of [0]",
            "msg.value == 0",
            "msg.value == 0",
            "msg.value one of [0]",
            "ori(tokenOwner$address) == 0",
            "ori(tokenApprovals$address) == 0",
            "msg.sender != 0",
            "ori(tokenBidder$address) == 0",
            "ori(tokenCurrentBid$uint256) == 0",
            "ori(tokenCurrentBid$uint256) == 0",
            "ori(tokenCurrentBid$uint256) one of [0]",
            "ori(tokenCreator$address) == ori(tokenOwner$address)",
            "ori(tokenCreator$address) == ori(tokenApprovals$address)",
            "ori(tokenCreator$address) != msg.sender",
            "ori(tokenCreator$address) == ori(tokenBidder$address)",
            "ori(tokenSalePrice$uint256) == msg.value",
            "ori(tokenSalePrice$uint256) >= msg.value",
            "ori(tokenSalePrice$uint256) <= msg.value",
            "ori(tokenSalePrice$uint256) == ori(tokenCurrentBid$uint256)",
            "ori(tokenSalePrice$uint256) >= ori(tokenCurrentBid$uint256)",
            "ori(tokenSalePrice$uint256) <= ori(tokenCurrentBid$uint256)",
            "msg.value == ori(tokenCurrentBid$uint256)",
            "msg.value >= ori(tokenCurrentBid$uint256)",
            "msg.value <= ori(tokenCurrentBid$uint256)",
            "ori(tokenOwner$address) == ori(tokenApprovals$address)",
            "ori(tokenOwner$address) != msg.sender",
            "ori(tokenOwner$address) == ori(tokenBidder$address)",
            "ori(tokenApprovals$address) != msg.sender",
            "ori(tokenApprovals$address) == ori(tokenBidder$address)",
            "msg.sender != ori(tokenBidder$address)"
        ],
        "postconditions": [
            "tokenOwner$address != 0",
            "tokenSold$bool == false",
            "tokenCurrentBid$uint256 == 0",
            "tokenCurrentBid$uint256 == 0",
            "tokenCurrentBid$uint256 one of [0]",
            "tokenSalePrice$uint256 == 0",
            "tokenSalePrice$uint256 == 0",
            "tokenSalePrice$uint256 one of [0]",
            "tokenBidder$address == 0",
            "tokenCreator$address != 0",
            "tokenApprovals$address == 0",
            "ori(tokenSold$bool) == tokenSold$bool",
            "ori(tokenCreator$address) != tokenOwner$address",
            "ori(tokenCreator$address) == tokenBidder$address",
            "ori(tokenCreator$address) != tokenCreator$address",
            "ori(tokenCreator$address) == tokenApprovals$address",
            "tokenOwner$address != ori(tokenOwner$address)",
            "tokenOwner$address != tokenBidder$address",
            "tokenOwner$address == tokenCreator$address",
            "tokenOwner$address != ori(tokenApprovals$address)",
            "tokenOwner$address == msg.sender",
            "tokenOwner$address != ori(tokenBidder$address)",
            "tokenOwner$address != tokenApprovals$address",
            "ori(tokenSalePrice$uint256) == tokenCurrentBid$uint256",
            "ori(tokenSalePrice$uint256) >= tokenCurrentBid$uint256",
            "ori(tokenSalePrice$uint256) <= tokenCurrentBid$uint256",
            "ori(tokenSalePrice$uint256) == tokenSalePrice$uint256",
            "ori(tokenSalePrice$uint256) >= tokenSalePrice$uint256",
            "ori(tokenSalePrice$uint256) <= tokenSalePrice$uint256",
            "msg.value == tokenCurrentBid$uint256",
            "msg.value >= tokenCurrentBid$uint256",
            "msg.value <= tokenCurrentBid$uint256",
            "msg.value == tokenSalePrice$uint256",
            "msg.value >= tokenSalePrice$uint256",
            "msg.value <= tokenSalePrice$uint256",
            "ori(tokenOwner$address) == tokenBidder$address",
            "ori(tokenOwner$address) != tokenCreator$address",
            "ori(tokenOwner$address) == tokenApprovals$address",
            "tokenCurrentBid$uint256 == tokenSalePrice$uint256",
            "tokenCurrentBid$uint256 >= tokenSalePrice$uint256",
            "tokenCurrentBid$uint256 <= tokenSalePrice$uint256",
            "tokenCurrentBid$uint256 == ori(tokenCurrentBid$uint256)",
            "tokenCurrentBid$uint256 >= ori(tokenCurrentBid$uint256)",
            "tokenCurrentBid$uint256 <= ori(tokenCurrentBid$uint256)",
            "tokenSalePrice$uint256 == ori(tokenCurrentBid$uint256)",
            "tokenSalePrice$uint256 >= ori(tokenCurrentBid$uint256)",
            "tokenSalePrice$uint256 <= ori(tokenCurrentBid$uint256)",
            "tokenBidder$address != tokenCreator$address",
            "tokenBidder$address == ori(tokenApprovals$address)",
            "tokenBidder$address != msg.sender",
            "tokenBidder$address == ori(tokenBidder$address)",
            "tokenBidder$address == tokenApprovals$address",
            "tokenCreator$address != ori(tokenApprovals$address)",
            "tokenCreator$address == msg.sender",
            "tokenCreator$address != ori(tokenBidder$address)",
            "tokenCreator$address != tokenApprovals$address",
            "ori(tokenApprovals$address) == tokenApprovals$address",
            "msg.sender != tokenApprovals$address",
            "ori(tokenBidder$address) == tokenApprovals$address"
        ]
    },
    {
        "func": "setSalePrice(_tokenId,_salePrice)@_tokenId",
        "type": "PptType.EXIT",
        "executionType": "TxType.NORMAL",
        "preconditions": [
            "_tokenId > 0",
            "msg.value == 0",
            "msg.value == 0",
            "msg.value one of [0]",
            "ori(tokenApprovals$address) == 0",
            "msg.sender != 0",
            "_salePrice > 0",
            "ori(tokenSalePrice$uint256) != _tokenId",
            "ori(tokenSalePrice$uint256) >= msg.value",
            "_tokenId >= msg.value",
            "_tokenId > msg.value",
            "_tokenId != msg.value",
            "_tokenId <= _salePrice",
            "_tokenId < _salePrice",
            "_tokenId != _salePrice",
            "_tokenId != ori(tokenCurrentBid$uint256)",
            "msg.value <= _salePrice",
            "msg.value < _salePrice",
            "msg.value != _salePrice",
            "msg.value <= ori(tokenCurrentBid$uint256)",
            "ori(tokenApprovals$address) != msg.sender",
            "msg.sender != ori(tokenBidder$address)",
            "_salePrice >= ori(tokenCurrentBid$uint256)",
            "_salePrice > ori(tokenCurrentBid$uint256)",
            "_salePrice != ori(tokenCurrentBid$uint256)"
        ],
        "postconditions": [
            "tokenApprovals$address == 0",
            "ori(tokenSold$bool) == tokenSold$bool",
            "ori(tokenCreator$address) == tokenCreator$address",
            "tokenOwner$address == ori(tokenOwner$address)",
            "_tokenId != tokenCurrentBid$uint256",
            "_tokenId != tokenSalePrice$uint256",
            "msg.value <= tokenCurrentBid$uint256",
            "msg.value <= tokenSalePrice$uint256",
            "tokenCurrentBid$uint256 <= tokenSalePrice$uint256",
            "tokenCurrentBid$uint256 <= _salePrice",
            "tokenCurrentBid$uint256 < _salePrice",
            "tokenCurrentBid$uint256 != _salePrice",
            "tokenCurrentBid$uint256 == ori(tokenCurrentBid$uint256)",
            "tokenCurrentBid$uint256 >= ori(tokenCurrentBid$uint256)",
            "tokenCurrentBid$uint256 <= ori(tokenCurrentBid$uint256)",
            "tokenSalePrice$uint256 <= _salePrice",
            "tokenSalePrice$uint256 >= ori(tokenCurrentBid$uint256)",
            "tokenBidder$address != msg.sender",
            "tokenBidder$address == ori(tokenBidder$address)",
            "ori(tokenApprovals$address) == tokenApprovals$address",
            "msg.sender != tokenApprovals$address"
        ]
    },
    {
        "func": "buy(_tokenId)@_tokenId",
        "type": "PptType.EXIT",
        "executionType": "TxType.NORMAL",
        "preconditions": [
            "_tokenId > 0",
            "msg.value > 0",
            "ori(tokenApprovals$address) == 0",
            "msg.sender != 0",
            "ori(tokenCurrentBid$uint256) one of [0,5000000000000000,50000000000000000,380000000000000000,150000000000000000,12000000000000000]",
            "ori(tokenCreator$address) != msg.sender",
            "ori(tokenSalePrice$uint256) != _tokenId",
            "ori(tokenSalePrice$uint256) <= msg.value",
            "ori(tokenSalePrice$uint256) >= ori(tokenCurrentBid$uint256)",
            "_tokenId <= msg.value",
            "_tokenId < msg.value",
            "_tokenId != msg.value",
            "_tokenId != ori(tokenCurrentBid$uint256)",
            "msg.value >= ori(tokenCurrentBid$uint256)",
            "msg.value > ori(tokenCurrentBid$uint256)",
            "msg.value != ori(tokenCurrentBid$uint256)",
            "ori(tokenOwner$address) != msg.sender",
            "ori(tokenApprovals$address) != msg.sender",
            "msg.sender != ori(tokenBidder$address)"
        ],
        "postconditions": [
            "tokenSold$bool == true",
            "tokenCurrentBid$uint256 == 0",
            "tokenCurrentBid$uint256 == 0",
            "tokenCurrentBid$uint256 one of [0]",
            "tokenSalePrice$uint256 == 0",
            "tokenSalePrice$uint256 == 0",
            "tokenSalePrice$uint256 one of [0]",
            "tokenBidder$address == 0",
            "tokenApprovals$address == 0",
            "ori(tokenCreator$address) == tokenCreator$address",
            "ori(tokenSalePrice$uint256) >= tokenCurrentBid$uint256",
            "ori(tokenSalePrice$uint256) >= tokenSalePrice$uint256",
            "_tokenId >= tokenCurrentBid$uint256",
            "_tokenId > tokenCurrentBid$uint256",
            "_tokenId != tokenCurrentBid$uint256",
            "_tokenId >= tokenSalePrice$uint256",
            "_tokenId > tokenSalePrice$uint256",
            "_tokenId != tokenSalePrice$uint256",
            "msg.value >= tokenCurrentBid$uint256",
            "msg.value > tokenCurrentBid$uint256",
            "msg.value != tokenCurrentBid$uint256",
            "msg.value >= tokenSalePrice$uint256",
            "msg.value > tokenSalePrice$uint256",
            "msg.value != tokenSalePrice$uint256",
            "tokenCurrentBid$uint256 == tokenSalePrice$uint256",
            "tokenCurrentBid$uint256 >= tokenSalePrice$uint256",
            "tokenCurrentBid$uint256 <= tokenSalePrice$uint256",
            "tokenCurrentBid$uint256 <= ori(tokenCurrentBid$uint256)",
            "tokenSalePrice$uint256 <= ori(tokenCurrentBid$uint256)",
            "tokenBidder$address == ori(tokenApprovals$address)",
            "tokenBidder$address != msg.sender",
            "tokenBidder$address == tokenApprovals$address",
            "tokenCreator$address != msg.sender",
            "ori(tokenApprovals$address) == tokenApprovals$address",
            "msg.sender != tokenApprovals$address"
        ]
    },
    {
        "func": "bid(_tokenId)@_tokenId",
        "type": "PptType.EXIT",
        "executionType": "TxType.NORMAL",
        "preconditions": [
            "_tokenId > 0",
            "msg.value > 0",
            "ori(tokenApprovals$address) == 0",
            "msg.sender != 0",
            "ori(tokenSalePrice$uint256) != _tokenId",
            "ori(tokenSalePrice$uint256) != msg.value",
            "_tokenId <= msg.value",
            "_tokenId < msg.value",
            "_tokenId != msg.value",
            "_tokenId != ori(tokenCurrentBid$uint256)",
            "msg.value >= ori(tokenCurrentBid$uint256)",
            "msg.value > ori(tokenCurrentBid$uint256)",
            "msg.value != ori(tokenCurrentBid$uint256)",
            "ori(tokenOwner$address) != msg.sender",
            "ori(tokenApprovals$address) != msg.sender"
        ],
        "postconditions": [
            "tokenCurrentBid$uint256 > 0",
            "tokenBidder$address != 0",
            "tokenApprovals$address == 0",
            "ori(tokenSold$bool) == tokenSold$bool",
            "ori(tokenCreator$address) == tokenCreator$address",
            "tokenOwner$address == ori(tokenOwner$address)",
            "tokenOwner$address != tokenBidder$address",
            "tokenOwner$address != msg.sender",
            "ori(tokenSalePrice$uint256) != tokenCurrentBid$uint256",
            "ori(tokenSalePrice$uint256) == tokenSalePrice$uint256",
            "ori(tokenSalePrice$uint256) >= tokenSalePrice$uint256",
            "ori(tokenSalePrice$uint256) <= tokenSalePrice$uint256",
            "_tokenId <= tokenCurrentBid$uint256",
            "_tokenId < tokenCurrentBid$uint256",
            "_tokenId != tokenCurrentBid$uint256",
            "_tokenId != tokenSalePrice$uint256",
            "msg.value == tokenCurrentBid$uint256",
            "msg.value >= tokenCurrentBid$uint256",
            "msg.value <= tokenCurrentBid$uint256",
            "msg.value != tokenSalePrice$uint256",
            "ori(tokenOwner$address) != tokenBidder$address",
            "tokenCurrentBid$uint256 != tokenSalePrice$uint256",
            "tokenCurrentBid$uint256 >= ori(tokenCurrentBid$uint256)",
            "tokenCurrentBid$uint256 > ori(tokenCurrentBid$uint256)",
            "tokenCurrentBid$uint256 != ori(tokenCurrentBid$uint256)",
            "tokenBidder$address != ori(tokenApprovals$address)",
            "tokenBidder$address == msg.sender",
            "tokenBidder$address != tokenApprovals$address",
            "ori(tokenApprovals$address) == tokenApprovals$address",
            "msg.sender != tokenApprovals$address"
        ]
    },
    {
        "func": "addNewTokenWithEditions(_uri,_editions,_salePrice)@uriOriginalToken[_uri]",
        "type": "PptType.EXIT",
        "executionType": "TxType.NORMAL",
        "preconditions": [
            "ori(tokenSold$bool) == false",
            "ori(tokenCreator$address) == 0",
            "ori(tokenSalePrice$uint256) == 0",
            "ori(tokenSalePrice$uint256) == 0",
            "ori(tokenSalePrice$uint256) one of [0]",
            "msg.value == 0",
            "msg.value == 0",
            "msg.value one of [0]",
            "ori(tokenOwner$address) == 0",
            "ori(tokenApprovals$address) == 0",
            "msg.sender != 0",
            "ori(tokenBidder$address) == 0",
            "_editions > 0",
            "_editions one of [2,4,5,6]",
            "_salePrice one of [100000000000000000,200000000000000000,300000000000000000,230000000000000000,0]",
            "ori(tokenCurrentBid$uint256) == 0",
            "ori(tokenCurrentBid$uint256) == 0",
            "ori(tokenCurrentBid$uint256) one of [0]",
            "ori(tokenCreator$address) == ori(tokenOwner$address)",
            "ori(tokenCreator$address) == ori(tokenApprovals$address)",
            "ori(tokenCreator$address) != msg.sender",
            "ori(tokenCreator$address) == ori(tokenBidder$address)",
            "ori(tokenSalePrice$uint256) == msg.value",
            "ori(tokenSalePrice$uint256) >= msg.value",
            "ori(tokenSalePrice$uint256) <= msg.value",
            "ori(tokenSalePrice$uint256) <= _editions",
            "ori(tokenSalePrice$uint256) < _editions",
            "ori(tokenSalePrice$uint256) != _editions",
            "ori(tokenSalePrice$uint256) <= _salePrice",
            "ori(tokenSalePrice$uint256) == ori(tokenCurrentBid$uint256)",
            "ori(tokenSalePrice$uint256) >= ori(tokenCurrentBid$uint256)",
            "ori(tokenSalePrice$uint256) <= ori(tokenCurrentBid$uint256)",
            "msg.value <= _editions",
            "msg.value < _editions",
            "msg.value != _editions",
            "msg.value <= _salePrice",
            "msg.value == ori(tokenCurrentBid$uint256)",
            "msg.value >= ori(tokenCurrentBid$uint256)",
            "msg.value <= ori(tokenCurrentBid$uint256)",
            "ori(tokenOwner$address) == ori(tokenApprovals$address)",
            "ori(tokenOwner$address) != msg.sender",
            "ori(tokenOwner$address) == ori(tokenBidder$address)",
            "ori(tokenApprovals$address) != msg.sender",
            "ori(tokenApprovals$address) == ori(tokenBidder$address)",
            "msg.sender != ori(tokenBidder$address)",
            "_editions != _salePrice",
            "_editions >= ori(tokenCurrentBid$uint256)",
            "_editions > ori(tokenCurrentBid$uint256)",
            "_editions != ori(tokenCurrentBid$uint256)",
            "_salePrice >= ori(tokenCurrentBid$uint256)"
        ],
        "postconditions": [
            "tokenSold$bool == false",
            "tokenCurrentBid$uint256 == 0",
            "tokenCurrentBid$uint256 == 0",
            "tokenCurrentBid$uint256 one of [0]",
            "tokenSalePrice$uint256 one of [0,230000000000000000,300000000000000000]",
            "tokenBidder$address == 0",
            "tokenApprovals$address == 0",
            "ori(tokenSold$bool) == tokenSold$bool",
            "ori(tokenCreator$address) == tokenBidder$address",
            "ori(tokenCreator$address) == tokenApprovals$address",
            "tokenOwner$address == tokenCreator$address",
            "ori(tokenSalePrice$uint256) == tokenCurrentBid$uint256",
            "ori(tokenSalePrice$uint256) >= tokenCurrentBid$uint256",
            "ori(tokenSalePrice$uint256) <= tokenCurrentBid$uint256",
            "ori(tokenSalePrice$uint256) <= tokenSalePrice$uint256",
            "msg.value == tokenCurrentBid$uint256",
            "msg.value >= tokenCurrentBid$uint256",
            "msg.value <= tokenCurrentBid$uint256",
            "msg.value <= tokenSalePrice$uint256",
            "ori(tokenOwner$address) == tokenBidder$address",
            "ori(tokenOwner$address) == tokenApprovals$address",
            "tokenCurrentBid$uint256 <= tokenSalePrice$uint256",
            "tokenCurrentBid$uint256 <= _editions",
            "tokenCurrentBid$uint256 < _editions",
            "tokenCurrentBid$uint256 != _editions",
            "tokenCurrentBid$uint256 <= _salePrice",
            "tokenCurrentBid$uint256 == ori(tokenCurrentBid$uint256)",
            "tokenCurrentBid$uint256 >= ori(tokenCurrentBid$uint256)",
            "tokenCurrentBid$uint256 <= ori(tokenCurrentBid$uint256)",
            "tokenSalePrice$uint256 != _editions",
            "tokenSalePrice$uint256 <= _salePrice",
            "tokenSalePrice$uint256 >= ori(tokenCurrentBid$uint256)",
            "tokenBidder$address == ori(tokenApprovals$address)",
            "tokenBidder$address != msg.sender",
            "tokenBidder$address == ori(tokenBidder$address)",
            "tokenBidder$address == tokenApprovals$address",
            "ori(tokenApprovals$address) == tokenApprovals$address",
            "msg.sender != tokenApprovals$address",
            "ori(tokenBidder$address) == tokenApprovals$address"
        ]
    },
    {
        "func": "cancelBid(_tokenId)@_tokenId",
        "type": "PptType.EXIT",
        "executionType": "TxType.NORMAL",
        "preconditions": [
            "ori(tokenSalePrice$uint256) one of [0,1000000000000000000,700000000000000000,2300000000000000000,2000000000000000000,250000000000000000,300000000000000000,1500000000000000000,1800000000000000000]",
            "_tokenId > 0",
            "msg.value == 0",
            "msg.value == 0",
            "msg.value one of [0]",
            "ori(tokenApprovals$address) == 0",
            "msg.sender != 0",
            "ori(tokenBidder$address) != 0",
            "ori(tokenCurrentBid$uint256) > 0",
            "ori(tokenCreator$address) != msg.sender",
            "ori(tokenCreator$address) != ori(tokenBidder$address)",
            "ori(tokenSalePrice$uint256) != _tokenId",
            "ori(tokenSalePrice$uint256) >= msg.value",
            "ori(tokenSalePrice$uint256) != ori(tokenCurrentBid$uint256)",
            "_tokenId >= msg.value",
            "_tokenId > msg.value",
            "_tokenId != msg.value",
            "_tokenId <= ori(tokenCurrentBid$uint256)",
            "_tokenId < ori(tokenCurrentBid$uint256)",
            "_tokenId != ori(tokenCurrentBid$uint256)",
            "msg.value <= ori(tokenCurrentBid$uint256)",
            "msg.value < ori(tokenCurrentBid$uint256)",
            "msg.value != ori(tokenCurrentBid$uint256)",
            "ori(tokenApprovals$address) != msg.sender",
            "ori(tokenApprovals$address) != ori(tokenBidder$address)",
            "msg.sender == ori(tokenBidder$address)"
        ],
        "postconditions": [
            "tokenCurrentBid$uint256 == 0",
            "tokenCurrentBid$uint256 == 0",
            "tokenCurrentBid$uint256 one of [0]",
            "tokenSalePrice$uint256 one of [0,1000000000000000000,700000000000000000,2300000000000000000,2000000000000000000,250000000000000000,300000000000000000,1500000000000000000,1800000000000000000]",
            "tokenBidder$address == 0",
            "tokenApprovals$address == 0",
            "ori(tokenSold$bool) == tokenSold$bool",
            "ori(tokenCreator$address) == tokenCreator$address",
            "tokenOwner$address == ori(tokenOwner$address)",
            "ori(tokenSalePrice$uint256) >= tokenCurrentBid$uint256",
            "ori(tokenSalePrice$uint256) == tokenSalePrice$uint256",
            "ori(tokenSalePrice$uint256) >= tokenSalePrice$uint256",
            "ori(tokenSalePrice$uint256) <= tokenSalePrice$uint256",
            "_tokenId >= tokenCurrentBid$uint256",
            "_tokenId > tokenCurrentBid$uint256",
            "_tokenId != tokenCurrentBid$uint256",
            "_tokenId != tokenSalePrice$uint256",
            "msg.value == tokenCurrentBid$uint256",
            "msg.value >= tokenCurrentBid$uint256",
            "msg.value <= tokenCurrentBid$uint256",
            "msg.value <= tokenSalePrice$uint256",
            "tokenCurrentBid$uint256 <= tokenSalePrice$uint256",
            "tokenCurrentBid$uint256 <= ori(tokenCurrentBid$uint256)",
            "tokenCurrentBid$uint256 < ori(tokenCurrentBid$uint256)",
            "tokenCurrentBid$uint256 != ori(tokenCurrentBid$uint256)",
            "tokenSalePrice$uint256 != ori(tokenCurrentBid$uint256)",
            "tokenBidder$address == ori(tokenApprovals$address)",
            "tokenBidder$address != msg.sender",
            "tokenBidder$address != ori(tokenBidder$address)",
            "tokenBidder$address == tokenApprovals$address",
            "tokenCreator$address != msg.sender",
            "tokenCreator$address != ori(tokenBidder$address)",
            "ori(tokenApprovals$address) == tokenApprovals$address",
            "msg.sender != tokenApprovals$address",
            "ori(tokenBidder$address) != tokenApprovals$address"
        ]
    },
    {
        "func": "acceptBid(_tokenId)@_tokenId",
        "type": "PptType.EXIT",
        "executionType": "TxType.NORMAL",
        "preconditions": [
            "ori(tokenCreator$address) != 0",
            "_tokenId > 0",
            "msg.value == 0",
            "msg.value == 0",
            "msg.value one of [0]",
            "ori(tokenOwner$address) != 0",
            "ori(tokenApprovals$address) == 0",
            "msg.sender != 0",
            "ori(tokenBidder$address) != 0",
            "ori(tokenCurrentBid$uint256) > 0",
            "ori(tokenCreator$address) != ori(tokenApprovals$address)",
            "ori(tokenCreator$address) != ori(tokenBidder$address)",
            "ori(tokenSalePrice$uint256) != _tokenId",
            "ori(tokenSalePrice$uint256) >= msg.value",
            "ori(tokenSalePrice$uint256) != ori(tokenCurrentBid$uint256)",
            "_tokenId >= msg.value",
            "_tokenId > msg.value",
            "_tokenId != msg.value",
            "_tokenId <= ori(tokenCurrentBid$uint256)",
            "_tokenId < ori(tokenCurrentBid$uint256)",
            "_tokenId != ori(tokenCurrentBid$uint256)",
            "msg.value <= ori(tokenCurrentBid$uint256)",
            "msg.value < ori(tokenCurrentBid$uint256)",
            "msg.value != ori(tokenCurrentBid$uint256)",
            "ori(tokenOwner$address) != ori(tokenApprovals$address)",
            "ori(tokenOwner$address) == msg.sender",
            "ori(tokenOwner$address) != ori(tokenBidder$address)",
            "ori(tokenApprovals$address) != msg.sender",
            "ori(tokenApprovals$address) != ori(tokenBidder$address)",
            "msg.sender != ori(tokenBidder$address)"
        ],
        "postconditions": [
            "tokenOwner$address != 0",
            "tokenSold$bool == true",
            "tokenCurrentBid$uint256 == 0",
            "tokenCurrentBid$uint256 == 0",
            "tokenCurrentBid$uint256 one of [0]",
            "tokenSalePrice$uint256 == 0",
            "tokenSalePrice$uint256 == 0",
            "tokenSalePrice$uint256 one of [0]",
            "tokenBidder$address == 0",
            "tokenCreator$address != 0",
            "tokenApprovals$address == 0",
            "ori(tokenCreator$address) != tokenOwner$address",
            "ori(tokenCreator$address) != tokenBidder$address",
            "ori(tokenCreator$address) == tokenCreator$address",
            "ori(tokenCreator$address) != tokenApprovals$address",
            "tokenOwner$address != ori(tokenOwner$address)",
            "tokenOwner$address != tokenBidder$address",
            "tokenOwner$address != tokenCreator$address",
            "tokenOwner$address != ori(tokenApprovals$address)",
            "tokenOwner$address != msg.sender",
            "tokenOwner$address == ori(tokenBidder$address)",
            "tokenOwner$address != tokenApprovals$address",
            "ori(tokenSalePrice$uint256) >= tokenCurrentBid$uint256",
            "ori(tokenSalePrice$uint256) >= tokenSalePrice$uint256",
            "_tokenId >= tokenCurrentBid$uint256",
            "_tokenId > tokenCurrentBid$uint256",
            "_tokenId != tokenCurrentBid$uint256",
            "_tokenId >= tokenSalePrice$uint256",
            "_tokenId > tokenSalePrice$uint256",
            "_tokenId != tokenSalePrice$uint256",
            "msg.value == tokenCurrentBid$uint256",
            "msg.value >= tokenCurrentBid$uint256",
            "msg.value <= tokenCurrentBid$uint256",
            "msg.value == tokenSalePrice$uint256",
            "msg.value >= tokenSalePrice$uint256",
            "msg.value <= tokenSalePrice$uint256",
            "ori(tokenOwner$address) != tokenBidder$address",
            "ori(tokenOwner$address) != tokenApprovals$address",
            "tokenCurrentBid$uint256 == tokenSalePrice$uint256",
            "tokenCurrentBid$uint256 >= tokenSalePrice$uint256",
            "tokenCurrentBid$uint256 <= tokenSalePrice$uint256",
            "tokenCurrentBid$uint256 <= ori(tokenCurrentBid$uint256)",
            "tokenCurrentBid$uint256 < ori(tokenCurrentBid$uint256)",
            "tokenCurrentBid$uint256 != ori(tokenCurrentBid$uint256)",
            "tokenSalePrice$uint256 <= ori(tokenCurrentBid$uint256)",
            "tokenSalePrice$uint256 < ori(tokenCurrentBid$uint256)",
            "tokenSalePrice$uint256 != ori(tokenCurrentBid$uint256)",
            "tokenBidder$address != tokenCreator$address",
            "tokenBidder$address == ori(tokenApprovals$address)",
            "tokenBidder$address != msg.sender",
            "tokenBidder$address != ori(tokenBidder$address)",
            "tokenBidder$address == tokenApprovals$address",
            "tokenCreator$address != ori(tokenApprovals$address)",
            "tokenCreator$address != ori(tokenBidder$address)",
            "tokenCreator$address != tokenApprovals$address",
            "ori(tokenApprovals$address) == tokenApprovals$address",
            "msg.sender != tokenApprovals$address",
            "ori(tokenBidder$address) != tokenApprovals$address"
        ]
    },
    {
        "func": "transfer(_to,_tokenId)@_tokenId",
        "type": "PptType.EXIT",
        "executionType": "TxType.NORMAL",
        "preconditions": [
            "ori(tokenSalePrice$uint256) one of [0,700000000000000000,1000000000000000000,200000000000000000,10000000000000000000,300000000000000000,500000000000000000,250000000000000000]",
            "_tokenId > 0",
            "msg.value == 0",
            "msg.value == 0",
            "msg.value one of [0]",
            "ori(tokenApprovals$address) == 0",
            "msg.sender != 0",
            "_to != 0",
            "ori(tokenCurrentBid$uint256) one of [0,80000000000000000,90000000000000000,100000000000000000,75000000000000000]",
            "ori(tokenSalePrice$uint256) != _tokenId",
            "ori(tokenSalePrice$uint256) >= msg.value",
            "_tokenId >= msg.value",
            "_tokenId > msg.value",
            "_tokenId != msg.value",
            "_tokenId != ori(tokenCurrentBid$uint256)",
            "msg.value <= ori(tokenCurrentBid$uint256)",
            "ori(tokenOwner$address) != _to",
            "ori(tokenApprovals$address) != msg.sender",
            "ori(tokenApprovals$address) != _to",
            "msg.sender != ori(tokenBidder$address)",
            "msg.sender != _to"
        ],
        "postconditions": [
            "tokenSold$bool == true",
            "tokenCurrentBid$uint256 one of [0,80000000000000000,90000000000000000,100000000000000000,75000000000000000]",
            "tokenSalePrice$uint256 == 0",
            "tokenSalePrice$uint256 == 0",
            "tokenSalePrice$uint256 one of [0]",
            "tokenApprovals$address == 0",
            "ori(tokenCreator$address) == tokenCreator$address",
            "tokenOwner$address != msg.sender",
            "ori(tokenSalePrice$uint256) >= tokenSalePrice$uint256",
            "_tokenId != tokenCurrentBid$uint256",
            "_tokenId >= tokenSalePrice$uint256",
            "_tokenId > tokenSalePrice$uint256",
            "_tokenId != tokenSalePrice$uint256",
            "msg.value <= tokenCurrentBid$uint256",
            "msg.value == tokenSalePrice$uint256",
            "msg.value >= tokenSalePrice$uint256",
            "msg.value <= tokenSalePrice$uint256",
            "tokenCurrentBid$uint256 >= tokenSalePrice$uint256",
            "tokenCurrentBid$uint256 == ori(tokenCurrentBid$uint256)",
            "tokenCurrentBid$uint256 >= ori(tokenCurrentBid$uint256)",
            "tokenCurrentBid$uint256 <= ori(tokenCurrentBid$uint256)",
            "tokenSalePrice$uint256 <= ori(tokenCurrentBid$uint256)",
            "tokenBidder$address != msg.sender",
            "tokenBidder$address == ori(tokenBidder$address)",
            "ori(tokenApprovals$address) == tokenApprovals$address",
            "msg.sender != tokenApprovals$address",
            "_to != tokenApprovals$address"
        ]
    }
]